dpgen2/__about__.py
dpgen2/__init__.py
dpgen2/__main__.py
dpgen2/_version.py
dpgen2/constants.py
dpgen2/conf/__init__.py
dpgen2/conf/alloy_conf.py
dpgen2/conf/conf_generator.py
dpgen2/conf/file_conf.py
dpgen2/conf/unit_cells.py
dpgen2/entrypoint/__init__.py
dpgen2/entrypoint/args.py
dpgen2/entrypoint/common.py
dpgen2/entrypoint/download.py
dpgen2/entrypoint/main.py
dpgen2/entrypoint/showkey.py
dpgen2/entrypoint/status.py
dpgen2/entrypoint/submit.py
dpgen2/entrypoint/watch.py
dpgen2/entrypoint/workflow.py
dpgen2/exploration/__init__.py
dpgen2/exploration/render/__init__.py
dpgen2/exploration/render/traj_render.py
dpgen2/exploration/render/traj_render_lammps.py
dpgen2/exploration/report/__init__.py
dpgen2/exploration/report/report.py
dpgen2/exploration/report/report_trust_levels.py
dpgen2/exploration/scheduler/__init__.py
dpgen2/exploration/scheduler/convergence_check_stage_scheduler.py
dpgen2/exploration/scheduler/scheduler.py
dpgen2/exploration/scheduler/stage_scheduler.py
dpgen2/exploration/selector/__init__.py
dpgen2/exploration/selector/conf_filter.py
dpgen2/exploration/selector/conf_selector.py
dpgen2/exploration/selector/conf_selector_frame.py
dpgen2/exploration/selector/trust_level.py
dpgen2/exploration/task/__init__.py
dpgen2/exploration/task/conf_sampling_task_group.py
dpgen2/exploration/task/lmp_template_task_group.py
dpgen2/exploration/task/make_task_group_from_config.py
dpgen2/exploration/task/npt_task_group.py
dpgen2/exploration/task/stage.py
dpgen2/exploration/task/task.py
dpgen2/exploration/task/lmp/__init__.py
dpgen2/exploration/task/lmp/lmp_input.py
dpgen2/flow/__init__.py
dpgen2/flow/dpgen_loop.py
dpgen2/fp/__init__.py
dpgen2/fp/gaussian.py
dpgen2/fp/prep_fp.py
dpgen2/fp/run_fp.py
dpgen2/fp/vasp.py
dpgen2/fp/vasp_input.py
dpgen2/op/__init__.py
dpgen2/op/collect_data.py
dpgen2/op/md_settings.py
dpgen2/op/prep_dp_train.py
dpgen2/op/prep_lmp.py
dpgen2/op/run_dp_train.py
dpgen2/op/run_lmp.py
dpgen2/op/select_confs.py
dpgen2/superop/__init__.py
dpgen2-0.0.7.dist-info/LICENSE
dpgen2-0.0.7.dist-info/METADATA
dpgen2-0.0.7.dist-info/WHEEL
dpgen2-0.0.7.dist-info/entry_points.txt
dpgen2-0.0.7.dist-info/top_level.txt
dpgen2-0.0.7.dist-info/RECORD
