Metadata-Version: 2.1
Name: dpgen2
Version: 0.0.7
Summary: DPGEN2: concurrent learning workflow generating the machine learning potential energy models.
Author: DeepModeling
License: GNU LESSER GENERAL PUBLIC LICENSE
Project-URL: Homepage, https://github.com/deepmodeling/dpgen2
Project-URL: documentation, https://docs.deepmodeling.com/projects/dpgen2
Project-URL: repository, https://github.com/deepmodeling/dpgen2
Keywords: deep potential,concurrent learning,work flow
Classifier: Programming Language :: Python :: 3.7
Classifier: License :: OSI Approved :: GNU Lesser General Public License v3 (LGPLv3)
Requires-Python: >=3.7
License-File: LICENSE
Requires-Dist: numpy
Requires-Dist: dpdata
Requires-Dist: pydflow (>=1.6.30)
Requires-Dist: dargs (>=0.3.1)
Requires-Dist: scipy
Requires-Dist: lbg
Requires-Dist: packaging
Provides-Extra: docs
Requires-Dist: sphinx ; extra == 'docs'
Requires-Dist: recommonmark ; extra == 'docs'
Requires-Dist: sphinx-rtd-theme (>=1.0.0rc1) ; extra == 'docs'
Requires-Dist: numpydoc ; extra == 'docs'
Requires-Dist: myst-parser ; extra == 'docs'
Requires-Dist: deepmodeling-sphinx ; extra == 'docs'
Requires-Dist: sphinx-argparse ; extra == 'docs'
Requires-Dist: dargs (>=0.3.1) ; extra == 'docs'
Provides-Extra: test
Requires-Dist: fakegaussian (>=0.0.3) ; extra == 'test'
